jfaleiro_tsstore/__init__.py
jfaleiro_tsstore/_version.py
jfaleiro_tsstore/dask.py
jfaleiro_tsstore/fastparquet.py
jfaleiro_tsstore/filesystem.py
jfaleiro_tsstore/tsstore.py
tests/__init__.py
tests/test_dask.py
tests/test_fastparquet.py
tests/test_python.py
tests/test_tsstore.py
jfaleiro.tsstore-0.0.1.dist-info/LICENSE
jfaleiro.tsstore-0.0.1.dist-info/METADATA
jfaleiro.tsstore-0.0.1.dist-info/WHEEL
jfaleiro.tsstore-0.0.1.dist-info/top_level.txt
jfaleiro.tsstore-0.0.1.dist-info/RECORD
