Metadata-Version: 2.1
Name: jfaleiro.tsstore
Version: 0.0.1
Summary: tsstore - Fast and simple timeseries storage
Home-page: https://gitlab.com/jfaleiro/tsstore
Author: Jorge M. Faleiro Jr.
Author-email: j@falei.ro
License: Affero GPL, see LICENSE.txt for details
Download-URL: https://gitlab.com/jfaleiro/tsstore/-/archive/master/tsstore-master.tar.gz
Platform: UNKNOWN
Classifier: Programming Language :: Python
Classifier: Programming Language :: Python :: 3
Classifier: Development Status :: 4 - Beta
Classifier: Intended Audience :: Developers
Classifier: License :: OSI Approved :: GNU Affero General Public License v3
Classifier: Operating System :: OS Independent
Classifier: Topic :: Software Development
Classifier: Topic :: Software Development :: Libraries :: Python Modules
Requires-Dist: numpy
Requires-Dist: pandas
Provides-Extra: dask
Requires-Dist: dask[dataframe] ; extra == 'dask'
Provides-Extra: dev
Requires-Dist: mock ; extra == 'dev'
Requires-Dist: pytest ; extra == 'dev'
Requires-Dist: coverage ; extra == 'dev'
Requires-Dist: behave ; extra == 'dev'
Requires-Dist: pyhamcrest ; extra == 'dev'
Requires-Dist: pre-commit ; extra == 'dev'
Requires-Dist: autopep8 ; extra == 'dev'
Requires-Dist: isort ; extra == 'dev'
Requires-Dist: pylint ; extra == 'dev'
Requires-Dist: flake8 ; extra == 'dev'
Requires-Dist: rope ; extra == 'dev'
Provides-Extra: fastparquet
Requires-Dist: fastparquet ; extra == 'fastparquet'
